euchre/__init__.py
euchre/root.py
euchre/abstract/__init__.py
euchre/abstract/card.py
euchre/abstract/computer.py
euchre/abstract/face.py
euchre/abstract/human.py
euchre/abstract/player.py
euchre/abstract/suit.py
euchre/abstract/team.py
euchre/command/__init__.py
euchre/command/play.py
euchre/command/rules.py
euchre/util/__init__.py
euchre/util/card_util.py
euchre/util/input_util.py
euchre/util/log_util.py
euchre/util/output_util.py
euchre/util/player_util.py
euchre/util/rule_util.py
euchre_cli-0.7.0.dist-info/entry_points.txt
euchre_cli-0.7.0.dist-info/LICENSE
euchre_cli-0.7.0.dist-info/WHEEL
euchre_cli-0.7.0.dist-info/METADATA
euchre_cli-0.7.0.dist-info/RECORD
