Metadata-Version: 2.1
Name: euchre-cli
Version: 0.7.0
Summary: Play euchre in your terminal.
Author-email: Bradley Wojcik <bradleycwojcik@gmail.com>
Requires-Python: >=3.10
Classifier: License :: OSI Approved :: MIT License
Requires-Dist: click >=8
Requires-Dist: names ==0.3.0
Requires-Dist: loguru >=0.5.0
Requires-Dist: black ; extra == "dev"
Requires-Dist: flake8 ; extra == "dev"
Requires-Dist: flit ; extra == "dev"
Requires-Dist: isort ; extra == "dev"
Requires-Dist: pre-commit ; extra == "dev"
Requires-Dist: homebrew-pypi-poet ; extra == "dev"
Requires-Dist: refurb ; extra == "dev"
Requires-Dist: pytest >=6 ; extra == "test"
Requires-Dist: pytest-cov ; extra == "test"
Requires-Dist: pytest-mock ; extra == "test"
Project-URL: Home, https://boldandbrad.github.io/euchre-cli/
Project-URL: Source, https://github.com/boldandbrad/euchre-cli
Provides-Extra: dev
Provides-Extra: test
